sampyl/__init__.py
sampyl/api.py
sampyl/core.py
sampyl/distributions.py
sampyl/exceptions.py
sampyl/model.py
sampyl/parallel.py
sampyl/posterior.py
sampyl/progressbar.py
sampyl/starting.py
sampyl/state.py
sampyl/stats.py
sampyl/samplers/NUTS.py
sampyl/samplers/__init__.py
sampyl/samplers/base.py
sampyl/samplers/chain.py
sampyl/samplers/hamiltonian.py
sampyl/samplers/metropolis.py
sampyl/samplers/slice.py
sampyl_mcmc-0.3.dist-info/METADATA
sampyl_mcmc-0.3.dist-info/RECORD
sampyl_mcmc-0.3.dist-info/WHEEL
sampyl_mcmc-0.3.dist-info/top_level.txt
